ifood_databricks_alcatraz/__init__.py
ifood_databricks_alcatraz/anonimyzer.py
ifood_databricks_alcatraz/cpf_recognizer.py
ifood_databricks_alcatraz/person_address_recognizer.py
ifood_databricks_alcatraz/phone_br_recognizer.py
ifood_databricks_alcatraz/resources/__init__.py
ifood_databricks_alcatraz/resources/pt_BR_address-words.txt
ifood_databricks_alcatraz/resources/pt_BR_names.txt
ifood_databricks_alcatraz-0.1.29.dist-info/METADATA
ifood_databricks_alcatraz-0.1.29.dist-info/WHEEL
ifood_databricks_alcatraz-0.1.29.dist-info/RECORD
