Metadata-Version: 2.1
Name: ifood-databricks-alcatraz
Version: 0.1.29
Summary: The iFood Databricks Alcatraz library anonymizes PII data in a Spark DataFrame. It is designed to be used in Databricks notebooks and jobs.
Author: Security Engineering Team
Author-email: security-engineering@ifood.com.br
Requires-Python: >=3.10,<4.0
Classifier: Programming Language :: Python :: 3
Classifier: Programming Language :: Python :: 3.10
Classifier: Programming Language :: Python :: 3.11
Classifier: Programming Language :: Python :: 3.12
Requires-Dist: numpy (==1.26.4)
Requires-Dist: presidio-analyzer (>=2.2.354,<3.0.0)
Requires-Dist: presidio-anonymizer (>=2.2.354,<3.0.0)
Requires-Dist: scapy (<=3.7.3)
Requires-Dist: unidecode (>=1.3.8,<2.0.0)
